setup.py
rak_net/__init__.py
rak_net/connection.py
rak_net/server.py
rak_net.egg-info/PKG-INFO
rak_net.egg-info/SOURCES.txt
rak_net.egg-info/dependency_links.txt
rak_net.egg-info/requires.txt
rak_net.egg-info/top_level.txt
rak_net/constant/__init__.py
rak_net/constant/protocol_info.py
rak_net/handler/__init__.py
rak_net/handler/connection_request_handler.py
rak_net/handler/offline_ping_handler.py
rak_net/handler/online_ping_handler.py
rak_net/handler/open_connection_request_1_handler.py
rak_net/handler/open_connection_request_2_handler.py
rak_net/protocol/__init__.py
rak_net/protocol/ack.py
rak_net/protocol/acknowledgement.py
rak_net/protocol/connection_request.py
rak_net/protocol/connection_request_accepted.py
rak_net/protocol/disconnect.py
rak_net/protocol/frame.py
rak_net/protocol/frame_set.py
rak_net/protocol/incompatible_protocol_version.py
rak_net/protocol/nack.py
rak_net/protocol/new_incoming_connection.py
rak_net/protocol/offline_ping.py
rak_net/protocol/offline_pong.py
rak_net/protocol/online_ping.py
rak_net/protocol/online_pong.py
rak_net/protocol/open_connection_reply_1.py
rak_net/protocol/open_connection_reply_2.py
rak_net/protocol/open_connection_request_1.py
rak_net/protocol/open_connection_request_2.py
rak_net/protocol/packet.py
rak_net/utils/__init__.py
rak_net/utils/internet_address.py
rak_net/utils/reliability_tool.py
rak_net/utils/udp_server_socket.py