Metadata-Version: 1.1
Name: rak-net
Version: 1.7
Summary: Podrum's RakNet library.
Home-page: https://github.com/Podrum/rak_net
Author: Podrum
Author-email: UNKNOWN
License: MIT
Keywords: raknet,net,rak,python3
Platform: UNKNOWN
Classifier: Development Status :: 5 - Production/Stable
Classifier: Intended Audience :: Developers
Classifier: Topic :: Software Development :: Libraries
Classifier: License :: OSI Approved :: MIT License
Classifier: Programming Language :: Python :: 3.5
Classifier: Programming Language :: Python :: 3.6
Classifier: Programming Language :: Python :: 3.7
Classifier: Programming Language :: Python :: 3.8
Classifier: Programming Language :: Python :: 3.9
Classifier: Programming Language :: Python :: 3.10
